{
  "indexes": [
    {
      "collectionGroup": "sessions",
      "queryScope": "COLLECTION",
      "fields": [
        {
          "fieldPath": "meta.date_start",
          "order": "DESCENDING"
        },
        {
          "fieldPath": "summary.laps",
          "order": "DESCENDING"
        }
      ]
    },
    {
      "collectionGroup": "sessions",
      "queryScope": "COLLECTION",
      "fields": [
        {
          "fieldPath": "meta.session_type",
          "order": "ASCENDING"
        },
        {
          "fieldPath": "meta.date_start",
          "order": "DESCENDING"
        }
      ]
    },
    {
      "collectionGroup": "sessions",
      "queryScope": "COLLECTION",
      "fields": [
        {
          "fieldPath": "meta.session_type",
          "order": "ASCENDING"
        },
        {
          "fieldPath": "meta.date_start",
          "order": "DESCENDING"
        },
        {
          "fieldPath": "summary.laps",
          "order": "DESCENDING"
        }
      ]
    },
    {
      "collectionGroup": "pilotDirectory",
      "queryScope": "COLLECTION",
      "fields": [
        {
          "fieldPath": "coachId",
          "order": "ASCENDING"
        },
        {
          "fieldPath": "role",
          "order": "ASCENDING"
        },
        {
          "fieldPath": "directorySortName",
          "order": "ASCENDING"
        },
        {
          "fieldPath": "__name__",
          "order": "ASCENDING"
        }
      ]
    },
    {
      "collectionGroup": "pilotDirectory",
      "queryScope": "COLLECTION",
      "fields": [
        {
          "fieldPath": "searchPrefixes",
          "arrayConfig": "CONTAINS"
        },
        {
          "fieldPath": "directorySortName",
          "order": "ASCENDING"
        },
        {
          "fieldPath": "__name__",
          "order": "ASCENDING"
        }
      ]
    },
    {
      "collectionGroup": "pilotDirectory",
      "queryScope": "COLLECTION",
      "fields": [
        {
          "fieldPath": "coachId",
          "order": "ASCENDING"
        },
        {
          "fieldPath": "role",
          "order": "ASCENDING"
        },
        {
          "fieldPath": "searchPrefixes",
          "arrayConfig": "CONTAINS"
        },
        {
          "fieldPath": "directorySortName",
          "order": "ASCENDING"
        },
        {
          "fieldPath": "__name__",
          "order": "ASCENDING"
        }
      ]
    }
  ],
  "fieldOverrides": []
}
